{
  "topic": {
    "id": "english_c1_conditions",
    "name": "English Grammar - Conditionals Mastery Test",
    "description": "Advanced questions covering all types of English conditionals for C1 level mastery",
    "tests": [
      {
        "test_id": "conditionals_c1",
        "test_title": "Advanced English Conditionals Test",
        "questions": [
          {
            "question_id": "q1",
            "question_text": "Which sentence correctly uses the zero conditional?",
            "options": [
              { "option_id": "a", "text": "If you heat water to 100째C, it boils." },
              { "option_id": "b", "text": "If you heat water to 100째C, it will boil." },
              { "option_id": "c", "text": "If you heated water to 100째C, it would boil." },
              { "option_id": "d", "text": "If you heat water to 100째C, it boiled." }
            ],
            "correct_option_id": "a"
          },
          {
            "question_id": "q2",
            "question_text": "Identify the correct first conditional sentence:",
            "options": [
              { "option_id": "a", "text": "If it rains tomorrow, we will cancel the picnic." },
              { "option_id": "b", "text": "If it rained tomorrow, we cancel the picnic." },
              { "option_id": "c", "text": "If it rains tomorrow, we cancel the picnic." },
              { "option_id": "d", "text": "If it will rain tomorrow, we will cancel the picnic." }
            ],
            "correct_option_id": "a"
          },
          {
            "question_id": "q3",
            "question_text": "Choose the sentence that uses the second conditional correctly:",
            "options": [
              { "option_id": "a", "text": "If I won the lottery, I would travel the world." },
              { "option_id": "b", "text": "If I win the lottery, I would travel the world." },
              { "option_id": "c", "text": "If I won the lottery, I will travel the world." },
              { "option_id": "d", "text": "If I would win the lottery, I would travel the world." }
            ],
            "correct_option_id": "a"
          },
          {
            "question_id": "q4",
            "question_text": "Which sentence correctly uses the third conditional?",
            "options": [
              { "option_id": "a", "text": "If she had studied harder, she would have passed the exam." },
              { "option_id": "b", "text": "If she studied harder, she would pass the exam." },
              { "option_id": "c", "text": "If she would have studied harder, she passed the exam." },
              { "option_id": "d", "text": "If she had studied harder, she will have passed the exam." }
            ],
            "correct_option_id": "a"
          },
          {
            "question_id": "q5",
            "question_text": "Select the sentence that correctly combines the second and third conditionals:",
            "options": [
              { "option_id": "a", "text": "If I had known, I would be there now." },
              { "option_id": "b", "text": "If I knew, I would have been there." },
              { "option_id": "c", "text": "If I would have known, I would be there now." },
              { "option_id": "d", "text": "If I had known, I would have been there." }
            ],
            "correct_option_id": "a"
          },
          {
            "question_id": "q6",
            "question_text": "Which sentence expresses a real possibility using the mixed conditional?",
            "options": [
              { "option_id": "a", "text": "If she were more confident, she would have accepted the job." },
              { "option_id": "b", "text": "If she had accepted the job, she would be more confident now." },
              { "option_id": "c", "text": "If she accepts the job, she would be confident now." },
              { "option_id": "d", "text": "If she were accepting the job, she would have been confident." }
            ],
            "correct_option_id": "b"
          },
          {
            "question_id": "q7",
            "question_text": "Choose the correct sentence using the inverted conditional form:",
            "options": [
              { "option_id": "a", "text": "Had I known, I would have helped you." },
              { "option_id": "b", "text": "If I had known, I would have helped you." },
              { "option_id": "c", "text": "Had I knew, I would help you." },
              { "option_id": "d", "text": "If I knew, had I helped you." }
            ],
            "correct_option_id": "a"
          },
          {
            "question_id": "q8",
            "question_text": "Identify the sentence using 'unless' correctly as a conditional substitute:",
            "options": [
              { "option_id": "a", "text": "I won't go unless it stops raining." },
              { "option_id": "b", "text": "Unless it will stop raining, I won't go." },
              { "option_id": "c", "text": "Unless it stopped raining, I won't go." },
              { "option_id": "d", "text": "I won't go unless it stopped raining." }
            ],
            "correct_option_id": "a"
          },
          {
            "question_id": "q9",
            "question_text": "Which sentence correctly uses the conditional with 'wish' to express regret?",
            "options": [
              { "option_id": "a", "text": "I wish I had taken that opportunity." },
              { "option_id": "b", "text": "I wish I take that opportunity." },
              { "option_id": "c", "text": "I wish I will take that opportunity." },
              { "option_id": "d", "text": "I wish I took that opportunity." }
            ],
            "correct_option_id": "a"
          },
          {
            "question_id": "q10",
            "question_text": "Choose the sentence that correctly uses the future real conditional:",
            "options": [
              { "option_id": "a", "text": "If they finish early, they will join us for dinner." },
              { "option_id": "b", "text": "If they finished early, they will join us for dinner." },
              { "option_id": "c", "text": "If they finished early, they would join us for dinner." },
              { "option_id": "d", "text": "If they will finish early, they join us for dinner." }
            ],
            "correct_option_id": "a"
          }
        ]
      }
    ]
  }
}
